pristy_support/__init__.py
pristy_support/__main__.py
pristy_support/cli.py
pristy_support/config_manager.py
pristy_support/exporters/__init__.py
pristy_support/exporters/html.py
pristy_support/exporters/markdown.py
pristy_support/exporters/zip_exporter.py
pristy_support/modules/__init__.py
pristy_support/modules/access_logs.py
pristy_support/modules/config.py
pristy_support/modules/database.py
pristy_support/modules/logs.py
pristy_support/modules/solr.py
pristy_support/modules/system.py
pristy_support/utils/__init__.py
pristy_support/utils/docker_utils.py
pristy_support/utils/logger.py
pristy_support/utils/permissions.py
pristy_support-1.3.0.dist-info/METADATA
pristy_support-1.3.0.dist-info/WHEEL
pristy_support-1.3.0.dist-info/entry_points.txt
pristy_support-1.3.0.dist-info/licenses/LICENSE
pristy_support-1.3.0.dist-info/RECORD
