Metadata-Version: 2.4
Name: pristy-support
Version: 1.3.0
Summary: Audit and support tools for Pristy ECM installations
Project-URL: Homepage, https://gitlab.com/pristy-oss/pristy-support
Project-URL: Documentation, https://gitlab.com/pristy-oss/pristy-support/blob/main/README.md
Project-URL: Repository, https://gitlab.com/pristy-oss/pristy-support.git
Project-URL: Bug Tracker, https://gitlab.com/pristy-oss/pristy-support/issues
Author-email: Jérémie Lesage <jeremie.lesage@jeci.fr>
Maintainer-email: Jérémie Lesage <jeremie.lesage@jeci.fr>
License: AGPL-3.0-or-later
License-File: LICENSE
Keywords: alfresco,audit,monitoring,pristy,support
Classifier: Development Status :: 4 - Beta
Classifier: Environment :: Console
Classifier: Intended Audience :: System Administrators
Classifier: License :: OSI Approved :: GNU Affero General Public License v3 or later (AGPLv3+)
Classifier: Operating System :: POSIX :: Linux
Classifier: Programming Language :: Python :: 3
Classifier: Programming Language :: Python :: 3.9
Classifier: Programming Language :: Python :: 3.10
Classifier: Programming Language :: Python :: 3.11
Classifier: Programming Language :: Python :: 3.12
Classifier: Programming Language :: Python :: 3.13
Classifier: Topic :: System :: Systems Administration
Requires-Python: >=3.9
Requires-Dist: click>=8.0
Requires-Dist: docker>=6.0.0
Requires-Dist: jinja2>=3.0
Requires-Dist: psutil>=5.9.0
Requires-Dist: python-dateutil>=2.8.0
Requires-Dist: pyyaml>=6.0
Requires-Dist: tabulate>=0.9.0
Provides-Extra: dev
Requires-Dist: black>=23.0; extra == 'dev'
Requires-Dist: flake8>=6.0; extra == 'dev'
Requires-Dist: mypy>=1.0; extra == 'dev'
Requires-Dist: pytest-cov>=4.0; extra == 'dev'
Requires-Dist: pytest>=7.0; extra == 'dev'
